plpygis/__init__.py
plpygis/_version.py
plpygis/exceptions.py
plpygis/geometry.py
plpygis/hex.py
plpygis/wkt.py
plpygis-0.6.1.dist-info/licenses/LICENSE
plpygis-0.6.1.dist-info/METADATA
plpygis-0.6.1.dist-info/WHEEL
plpygis-0.6.1.dist-info/top_level.txt
plpygis-0.6.1.dist-info/RECORD
