Metadata-Version: 2.4
Name: plpygis
Version: 0.6.1
Summary: Python tools for PostGIS
Author-email: Benjamin Trigona-Harany <plpygis@jaxartes.net>
License: GPL-3.0-only
Project-URL: Homepage, https://github.com/bosth/plpygis
Project-URL: Issues, https://github.com/bosth/plpygis/issues
Project-URL: Documentation, https://plpygis.readthedocs.io/
Keywords: gis,geospatial,postgis,postgresql,pl/python
Classifier: Topic :: Database
Classifier: Topic :: Scientific/Engineering :: GIS
Requires-Python: >=3.9
License-File: LICENSE
Provides-Extra: test
Requires-Dist: pytest; extra == "test"
Requires-Dist: pyshp; extra == "test"
Requires-Dist: Shapely>=2.0.4; extra == "test"
Provides-Extra: shapely-support
Requires-Dist: Shapely>=2.0.4; extra == "shapely-support"
Dynamic: license-file
